setup.py
raw_data_emca.egg-info/.gitignore
raw_data_emca.egg-info/PKG-INFO
raw_data_emca.egg-info/SOURCES.txt
raw_data_emca.egg-info/dependency_links.txt
raw_data_emca.egg-info/entry_points.txt
raw_data_emca.egg-info/requires.txt
raw_data_emca.egg-info/top_level.txt
rawdata_emca/__init__.py
rawdata_emca/connections/__init__.py
rawdata_emca/connections/built_in.py
rawdata_emca/connections/connect_db.py
rawdata_emca/connections/connect_db_where.py
rawdata_emca/connections/mock.py
rawdata_emca/connections/mock_fail.py
rawdata_emca/errors/__init__.py
rawdata_emca/errors/data_error.py
rawdata_emca/processor/__init__.py
rawdata_emca/processor/built_in.py
rawdata_emca/processor/custom_processors.py
rawdata_emca/processor/field_description.py
rawdata_emca/processor/mock.py
rawdata_emca/processor/rawcsvsort.py
rawdata_emca/runner/__init__.py
rawdata_emca/runner/config_entry.py
rawdata_emca/runner/config_file_reader.py
rawdata_emca/runner/entry.py
rawdata_emca/runner/raw_data_cli.py
rawdata_emca/runner/raw_processor.py
rawdata_emca/runner/test_runner.py
rawdata_emca/utilities/__init__.py
rawdata_emca/utilities/factory.py