Metadata-Version: 1.1
Name: raw-data-emca
Version: 0.9.2
Summary: application to help data analyst, Extract, Manipulate, Clean, and Analyze their data
Home-page: https://github.com/jkbowle/RawDataProcessing
Author: Jason Bowles
Author-email: jaykbowles@gmail.com
License: MIT
Platform: any
Classifier: Development Status :: 3 - Alpha
Classifier: Intended Audience :: Developers
Classifier: Topic :: Software Development :: Build Tools
Classifier: License :: OSI Approved :: MIT License
Classifier: Programming Language :: Python :: 2.7
